{
    "sortBy": ["최신순", "인기순", "낮은 가격 순", "높은 가격 순"],
    "brand": [
        "adidas originals",
        "asics",
        "calvin klein",
        "carhartt",
        "champion",
        "converse",
        "fila",
        "kappa",
        "lacoste",
        "le coq sportif",
        "new balance",
        "nike",
        "puma",
        "reebok",
        "stussy",
        "the north face",
        "tommy hilfiger",
        "vans"
    ],
    "category": {
        "의류": {
            "productType": [
                "가디건",
                "긴팔 티셔츠",
                "니트",
                "반팔 티셔츠",
                "셔츠",
                "스웨터",
                "패딩",
                "후드",
                "바지",
                "반바지"
            ],
            "sizeArray": ["XS", "S", "M", "L", "XL", "XXL", "XXXL"]
        },
        "신발": {
            "productType": ["스니커즈", "단화", "장화", "운동화"],
            "sizeArray": [
                "220",
                "225",
                "230",
                "235",
                "240",
                "245",
                "250",
                "255",
                "260",
                "265",
                "270",
                "275",
                "280",
                "285",
                "290",
                "295",
                "300"
            ]
        },
        "기타": { "productType": ["악세서리", "지갑", "모자", "가방", "기타"], "sizeArray": ["one size"] },
        "전체": {
            "productType": [
                "가디건",
                "긴팔 티셔츠",
                "니트",
                "반팔 티셔츠",
                "셔츠",
                "스웨터",
                "패딩",
                "후드",
                "바지",
                "반바지",
                "악세서리",
                "지갑",
                "모자",
                "가방",
                "기타",
                "스니커즈",
                "단화",
                "장화",
                "운동화"
            ],
            "sizeArray": [
                "220",
                "225",
                "230",
                "235",
                "240",
                "245",
                "250",
                "255",
                "260",
                "265",
                "270",
                "275",
                "280",
                "285",
                "290",
                "295",
                "300",
                "XS",
                "S",
                "M",
                "L",
                "XL",
                "XXL",
                "XXXL",
                "one size"
            ]
        }
    },
    "intl": ["해외배송", "국내배송"],
    "price": [0, 1000000]
}
